PlayDrissionPage/__init__.py
PlayDrissionPage/client/__init__.py
PlayDrissionPage/client/remote_browser_client.py
PlayDrissionPage/models/__init__.py
PlayDrissionPage/models/base.py
PlayDrissionPage/models/debugger.py
PlayDrissionPage/page_addition/__init__.py
PlayDrissionPage/page_addition/event_listener.py
PlayDrissionPage/page_addition/page_plus.py
PlayDrissionPage-0.0.3.1.dist-info/METADATA
PlayDrissionPage-0.0.3.1.dist-info/WHEEL
PlayDrissionPage-0.0.3.1.dist-info/entry_points.txt
PlayDrissionPage-0.0.3.1.dist-info/top_level.txt
PlayDrissionPage-0.0.3.1.dist-info/RECORD
