Metadata-Version: 2.1
Name: PlayDrissionPage
Version: 0.0.3.1
Summary: Playwright and DrissionPage
Home-page: https://gitee.com/xx299x/PlayDrissionPage
Author: xx299x
Author-email: xx299x@gmail.com
License: BSD
Keywords: Playwright,DrissionPage
Classifier: Programming Language :: Python :: 3.6
Classifier: Development Status :: 4 - Beta
Classifier: Topic :: Utilities
Classifier: License :: OSI Approved :: BSD License
Requires-Python: >=3.6
Requires-Dist: DrissionPage ==4.1.0.14
Requires-Dist: playwright ==1.49.1
Requires-Dist: requests
